{"Items":[{"ModelID":"1","Duration":1440.0,"VirtualChestModels":[{"ModelID":"0","Reward":250,"CurrencyID":"0","Treshold":0.5},{"ModelID":"1","Reward":250,"CurrencyID":"0","Treshold":1.0}]},{"ModelID":"2","Duration":1440.0,"VirtualChestModels":[{"ModelID":"2","Reward":250,"CurrencyID":"0","Treshold":0.5},{"ModelID":"3","Reward":250,"CurrencyID":"0","Treshold":1.0}]},{"ModelID":"3","Duration":1440.0,"VirtualChestModels":[{"ModelID":"4","Reward":250,"CurrencyID":"0","Treshold":0.5},{"ModelID":"5","Reward":250,"CurrencyID":"0","Treshold":1.0}]},{"ModelID":"4","Duration":1440.0,"VirtualChestModels":[{"ModelID":"6","Reward":250,"CurrencyID":"0","Treshold":0.5},{"ModelID":"7","Reward":250,"CurrencyID":"0","Treshold":1.0}]}]}