{"skeleton":{"hash":"tZaywGVpdA/nlctAgtr3CWfSVVw","spine":"3.8.82","x":-145.05,"y":3.27,"width":307,"height":172.93,"images":"","audio":""},"bones":[{"name":"root"},{"name":"hip","parent":"root","x":-6.01,"y":51.16},{"name":"body1","parent":"hip","length":24.17,"rotation":152.78,"x":-1.23,"y":1.07,"color":"ff0000ff"},{"name":"body2","parent":"body1","length":33.7,"rotation":-32.72,"x":23.99,"y":0.33,"color":"ff0000ff"},{"name":"shoulder_l","parent":"body2","rotation":-95.91,"x":15.14,"y":-10.36,"transform":"noScale"},{"name":"hand_l_IK","parent":"root","x":32.65,"y":110.62,"color":"000affff"},{"name":"hand_l1","parent":"shoulder_l","length":28.08,"rotation":-4.26,"x":3.19,"y":-0.58,"color":"000affff"},{"name":"hand_l2","parent":"hand_l1","length":30.44,"rotation":11.78,"x":33.45,"y":0.91,"color":"000affff"},{"name":"arm_l","parent":"hand_l2","length":13.78,"rotation":-95.87,"x":36.44,"y":-3.5,"color":"000affff"},{"name":"shoulder_r","parent":"body2","rotation":140.46,"x":27,"y":-0.26,"transform":"noScale"},{"name":"hand_r_IK","parent":"root","x":-3.06,"y":20.23,"color":"00ff36ff"},{"name":"hand_r1","parent":"shoulder_r","length":40.57,"rotation":6.87,"x":4.2,"y":0.3,"color":"00ff36ff"},{"name":"hand_r2","parent":"hand_r1","length":37.51,"rotation":70.42,"x":46.76,"y":5.5,"color":"00ff36ff"},{"name":"hand_r3","parent":"hand_r2","length":13.52,"rotation":-8.63,"x":44.86,"y":4.99,"color":"00ff36ff"},{"name":"head","parent":"body2","length":45.29,"rotation":-23.43,"x":35.72,"y":1.54,"transform":"noScale","color":"fc007fff"},{"name":"leg_IK","parent":"root","x":100.35,"y":22.08,"color":"ffbd00ff"},{"name":"leg1","parent":"hip","length":54.4,"rotation":9.99,"x":23.97,"y":-9.34,"color":"ffbd00ff"},{"name":"leg2","parent":"leg1","length":31.42,"rotation":-58.11,"x":59.65,"y":-5.96,"color":"ffbd00ff"},{"name":"leg3","parent":"leg2","length":21.22,"rotation":71.34,"x":33.79,"y":4.64,"color":"ffbd00ff"},{"name":"pillow1_action","parent":"root","x":-64.17,"y":98.92},{"name":"pillow1_shadows","parent":"pillow1_action","x":-9.57,"y":-6.06},{"name":"womb","parent":"hip","length":133.51,"rotation":8.6,"x":0.31,"y":-0.92}],"slots":[{"name":"mask","bone":"root","attachment":"mask"},{"name":"Кровать","bone":"root","attachment":"Кровать"},{"name":"Тень зеленая подушка","bone":"root","attachment":"Тень зеленая подушка"},{"name":"Зленая подушка","bone":"root","attachment":"Зленая подушка"},{"name":"Тень подушки в крапинку","bone":"root","attachment":"Тень подушки в крапинку"},{"name":"Подушка в крапинку","bone":"root","attachment":"Подушка в крапинку"},{"name":"Тень розовой подушки_action","bone":"root","attachment":"Тень розовой подушки"},{"name":"Тень розовой подушки","bone":"root"},{"name":"Розовая подушка_action","bone":"root","attachment":"Розовая подушка"},{"name":"Розовая подушка","bone":"root"},{"name":"Тень царицы","bone":"root","attachment":"Тень царицы"},{"name":"Плечо левое","bone":"root","attachment":"Плечо левое"},{"name":"Предплечье левое","bone":"root","attachment":"Предплечье левое"},{"name":"Матка","bone":"root","attachment":"Матка"},{"name":"Кисть левая","bone":"root","attachment":"Кисть левая"},{"name":"Туловище","bone":"root","attachment":"Туловище"},{"name":"Усик правый","bone":"root","attachment":"Усик правый"},{"name":"Усик левый","bone":"root","attachment":"Усик левый"},{"name":"Глаз левый","bone":"root","attachment":"Глаз левый"},{"name":"Зрачок левый","bone":"root","attachment":"Зрачок левый"},{"name":"Голова","bone":"root","attachment":"Голова"},{"name":"Глаз правый","bone":"root","attachment":"Глаз правый"},{"name":"Зрачок правый","bone":"root","attachment":"Зрачок правый"},{"name":"закрытые глаза","bone":"root","attachment":"закрытые глаза"},{"name":"Голень правая","bone":"root","attachment":"Голень правая"},{"name":"Бедро правое","bone":"root","attachment":"Бедро правое"},{"name":"Стопа правая","bone":"root","attachment":"Стопа правая"},{"name":"Плечо правое","bone":"root","attachment":"Плечо правое"},{"name":"Предпплечье правое","bone":"root","attachment":"Предпплечье левое"},{"name":"Кисть правая","bone":"root","attachment":"Кисть правая"},{"name":"happy_hand_right_path","bone":"root","attachment":"happy_hand_right_path"},{"name":"happy_hand_left_path","bone":"root","attachment":"happy_hand_right_path"}],"ik":[{"name":"hand_l_IK","order":4,"bones":["hand_l1","hand_l2"],"target":"hand_l_IK"},{"name":"hand_r_IK","order":2,"bones":["hand_r1","hand_r2"],"target":"hand_r_IK"},{"name":"leg_IK","bones":["leg1","leg2"],"target":"leg_IK","bendPositive":false}],"path":[{"name":"happy_hand_left_path_constr","order":3,"bones":["hand_l_IK"],"target":"happy_hand_left_path","rotateMix":0,"translateMix":0},{"name":"happy_hand_right_path_constr","order":1,"bones":["hand_r_IK"],"target":"happy_hand_right_path","translateMix":0}],"skins":[{"name":"default","attachments":{"happy_hand_left_path":{"happy_hand_right_path":{"type":"path","closed":true,"lengths":[65.35,130.69],"vertexCount":6,"vertices":[-36.72,146.32,-22.93,145.84,-9.15,145.35,-4.32,86.11,-18.1,86.6,-31.88,87.08]}},"happy_hand_right_path":{"happy_hand_right_path":{"type":"path","closed":true,"lengths":[65.35,130.69],"vertexCount":6,"vertices":[-62.87,146.32,-49.08,145.84,-35.3,145.35,-30.47,86.11,-44.25,86.6,-58.03,87.08]}},"mask":{"mask":{"type":"clipping","end":"mask","vertexCount":4,"vertices":[-224.54,237.49,-224.54,-68.72,279.72,-70.02,261.48,242.7],"color":"ce3a3aff"}},"Бедро правое":{"Бедро правое":{"type":"mesh","uvs":[1,1,0,1,0,0,1,0],"triangles":[1,2,3,1,3,0],"vertices":[1,16,60.05,-9.1,1,1,16,-6.94,-9.6,1,1,16,-7.08,8.4,1,1,16,59.92,8.9,1],"hull":4,"edges":[0,2,2,4,4,6,0,6],"width":67,"height":18}},"Глаз левый":{"Глаз левый":{"type":"mesh","uvs":[1,1,0,1,0,0,1,0],"triangles":[1,2,3,1,3,0],"vertices":[1,14,15.98,-37,1,1,14,21.07,6.7,1,1,14,59.81,2.19,1,1,14,54.72,-41.51,1],"hull":4,"edges":[0,2,2,4,4,6,0,6],"width":44,"height":39}},"Глаз правый":{"Глаз правый":{"type":"mesh","uvs":[1,1,0,1,0,0,1,0],"triangles":[1,2,3,1,3,0],"vertices":[1,14,14.2,-17.67,1,1,14,19.75,30.01,1,1,14,54.52,25.96,1,1,14,48.97,-21.71,1],"hull":4,"edges":[0,2,2,4,4,6,0,6],"width":48,"height":35}},"Голень правая":{"Голень правая":{"type":"mesh","uvs":[1,1,0,1,0,0,1,0],"triangles":[1,2,3,1,3,0],"vertices":[1,17,38.06,0.61,1,1,17,24.49,-21.57,1,1,17,-7.07,-2.25,1,1,17,6.5,19.92,1],"hull":4,"edges":[0,2,2,4,4,6,0,6],"width":26,"height":37}},"Голова":{"Голова":{"type":"mesh","uvs":[1,1,0,1,0,0,1,0],"triangles":[1,2,3,1,3,0],"vertices":[1,14,-7.63,-32.24,1,1,14,-0.34,30.34,1,1,14,49.32,24.56,1,1,14,42.04,-38.02,1],"hull":4,"edges":[0,2,2,4,4,6,0,6],"width":63,"height":50}},"Зленая подушка":{"Зленая подушка":{"x":-40.48,"y":76.77,"width":95,"height":99}},"Зрачок левый":{"Зрачок левый":{"type":"mesh","uvs":[1,1,0,1,0,0,1,0],"triangles":[1,2,3,1,3,0],"vertices":[1,14,34.14,-28.04,1,1,14,35.76,-14.14,1,1,14,50.66,-15.87,1,1,14,49.04,-29.78,1],"hull":4,"edges":[0,2,2,4,4,6,0,6],"width":14,"height":15}},"Зрачок правый":{"Зрачок правый":{"type":"mesh","uvs":[1,1,0,1,0,0,1,0],"triangles":[1,2,3,1,3,0],"vertices":[1,14,22.84,-12.63,1,1,14,25.04,6.24,1,1,14,40.93,4.39,1,1,14,38.74,-14.48,1],"hull":4,"edges":[0,2,2,4,4,6,0,6],"width":19,"height":16}},"Кисть левая":{"Кисть левая":{"type":"mesh","uvs":[1,1,0,1,0,0,1,0],"triangles":[1,2,3,1,3,0],"vertices":[1,8,23.86,5.29,1,1,8,14.28,-14.51,1,1,8,-4.62,-5.36,1,1,8,4.96,14.44,1],"hull":4,"edges":[0,2,2,4,4,6,0,6],"width":22,"height":21}},"Кисть правая":{"Кисть правая":{"type":"mesh","uvs":[1,1,0,1,0,0,1,0],"triangles":[1,2,3,1,3,0],"vertices":[1,13,19.37,-7.92,1,1,13,2.19,-18.16,1,1,13,-8.57,-0.13,1,1,13,8.61,10.12,1],"hull":4,"edges":[0,2,2,4,4,6,0,6],"width":20,"height":21}},"Кровать":{"Кровать":{"x":16.95,"y":34.27,"width":290,"height":62}},"Матка":{"Матка":{"type":"mesh","uvs":[1,1,0,1,0,0,1,0],"triangles":[1,2,3,1,3,0],"vertices":[1,21,126.92,-54.55,1,1,21,-10.51,-33.77,1,1,21,4.43,65.1,1,1,21,141.87,44.33,1],"hull":4,"edges":[0,2,2,4,4,6,0,6],"width":139,"height":100}},"Плечо левое":{"Плечо левое":{"type":"mesh","uvs":[1,1,0,1,0,0,1,0],"triangles":[1,2,3,1,3,0],"vertices":[1,6,29.88,-14.83,1,1,6,-5.85,-1.9,1,1,6,-0.06,14.09,1,1,6,35.67,1.15,1],"hull":4,"edges":[0,2,2,4,4,6,0,6],"width":38,"height":17}},"Плечо правое":{"Плечо правое":{"type":"mesh","uvs":[1,1,0,1,0,0,1,0],"triangles":[1,2,3,1,3,0],"vertices":[1,11,41.81,5.28,1,1,11,42.4,-7.71,1,1,11,-4.56,-9.84,1,1,11,-5.15,3.14,1],"hull":4,"edges":[0,2,2,4,4,6,0,6],"width":13,"height":47}},"Подушка в крапинку":{"Подушка в крапинку":{"x":-83.05,"y":63.77,"width":108,"height":97}},"Предплечье левое":{"Предплечье левое":{"type":"mesh","uvs":[1,1,0,1,0,0,1,0],"triangles":[1,2,3,1,3,0],"vertices":[1,7,27.68,-21.8,1,1,7,-3.81,-2.37,1,1,7,7.75,16.35,1,1,7,39.23,-3.08,1],"hull":4,"edges":[0,2,2,4,4,6,0,6],"width":37,"height":22}},"Предпплечье правое":{"Предпплечье левое":{"type":"mesh","uvs":[1,1,0,1,0,0,1,0],"triangles":[1,2,3,1,3,0],"vertices":[1,12,44.23,-2.52,1,1,12,2.56,-19.51,1,1,12,-7.63,5.49,1,1,12,34.03,22.48,1],"hull":4,"edges":[0,2,2,4,4,6,0,6],"width":45,"height":27}},"Розовая подушка":{"Розовая подушка":{"type":"mesh","uvs":[1,1,0,1,0,0,1,0],"triangles":[1,2,3,1,3,0],"vertices":[-15.05,44.27,-120.05,44.27,-120.05,141.27,-15.05,141.27],"hull":4,"edges":[0,2,2,4,4,6,0,6],"width":105,"height":97}},"Розовая подушка_action":{"Розовая подушка":{"type":"mesh","uvs":[1,1,0,1,0,0,1,0],"triangles":[1,2,3,1,3,0],"vertices":[1,19,49.12,-54.64,1,1,19,-55.88,-54.64,1,1,19,-55.88,42.36,1,1,19,49.12,42.36,1],"hull":4,"edges":[0,2,2,4,4,6,0,6],"width":105,"height":97}},"Стопа правая":{"Стопа правая":{"type":"mesh","uvs":[1,1,0,1,0,0,1,0],"triangles":[1,2,3,1,3,0],"vertices":[1,18,19.97,-10.43,1,1,18,-5.38,-4.67,1,1,18,-2.5,8.01,1,1,18,22.85,2.24,1],"hull":4,"edges":[0,2,2,4,4,6,0,6],"width":26,"height":13}},"Тень зеленая подушка":{"Тень зеленая подушка":{"x":-42.05,"y":69.77,"width":104,"height":107}},"Тень подушки в крапинку":{"Тень подушки в крапинку":{"x":-87.55,"y":54.77,"width":115,"height":103}},"Тень розовой подушки":{"Тень розовой подушки":{"type":"mesh","uvs":[1,1,0,1,0,0,1,0],"triangles":[1,2,3,1,3,0],"vertices":[-15.05,33.27,-128.05,33.27,-128.05,138.27,-15.05,138.27],"hull":4,"edges":[0,2,2,4,4,6,0,6],"width":113,"height":105}},"Тень розовой подушки_action":{"Тень розовой подушки":{"type":"mesh","uvs":[1,1,0,1,0,0,1,0],"triangles":[1,2,3,1,3,0],"vertices":[-15.05,33.27,-128.05,33.27,-128.05,138.27,-15.05,138.27],"hull":4,"edges":[0,2,2,4,4,6,0,6],"width":113,"height":105}},"Тень царицы":{"Тень царицы":{"type":"mesh","uvs":[0.00591,0.12333,0.07509,0.0353,0.18434,0.03286,0.23454,0.16735,0.1873,0.26272,0.21387,0.40943,0.28769,0.54148,0.38071,0.57083,0.5535,0.58262,0.77991,0.63706,0.97871,0.7489,0.91374,0.83938,0.80597,0.8785,0.89898,0.91518,0.95065,0.98121,0.88126,0.97876,0.78825,0.95675,0.73067,0.90785,0.58007,0.92741,0.44424,0.88339,0.33351,0.78803,0.30694,0.67799,0.23607,0.63397,0.12682,0.5435,0.11796,0.39433,0.09286,0.32831,0.02051,0.29163],"triangles":[15,13,14,15,16,13,16,12,13,16,17,12,9,17,18,18,19,8,17,9,12,9,18,8,19,20,8,8,20,7,12,9,11,11,9,10,20,21,7,22,6,21,21,6,7,22,23,6,23,5,6,23,24,5,24,4,5,24,25,4,25,26,4,26,0,4,4,0,3,3,0,1,3,1,2],"vertices":[-80.09,116.49,-69.13,127.76,-45.97,128.07,-33.14,108.66,-45.34,98.65,-40.33,80.18,-24.06,62.97,-4.34,59.21,32.29,57.7,79.04,46.66,122.44,36.42,108.66,24.83,85.81,19.83,105.53,15.13,116.49,6.68,101.78,6.99,82.06,9.81,69.85,16.07,37.93,13.57,9.13,19.2,-14.34,31.41,-19.98,45.49,-35,51.13,-58.16,62.71,-60.04,81.8,-61.29,92.44,-75.38,98.08],"hull":27,"edges":[0,2,2,4,4,6,6,8,8,10,10,12,12,14,14,16,20,22,22,24,24,26,26,28,28,30,30,32,32,34,34,36,36,38,38,40,40,42,42,44,44,46,46,48,48,50,50,52,16,18,18,20,0,52],"width":212,"height":128}},"Туловище":{"Туловище":{"type":"mesh","uvs":[0.21911,0.11462,0.45054,0.18517,0.57997,0.31873,0.64768,0.63121,0.82597,0.82525,0.98539,0.87061,0.94939,1,0.79511,0.98905,0.50368,0.94453,0.31254,0.83785,0.18308,0.66525,0.06825,0.49933,0.02125,0.29706,0.01029,0.07094,0.10854,0.02138],"triangles":[9,10,3,10,2,3,2,11,1,1,11,0,11,2,10,11,12,0,0,13,14,0,12,13,5,6,4,6,7,4,7,8,4,8,3,4,8,9,3],"vertices":[2,2,44.72,-21.2,0.00527,3,29.02,-6.88,0.99473,2,2,33.03,-23.25,0.13214,3,20.29,-14.93,0.86786,2,2,22.33,-19.26,0.47089,3,9.13,-17.35,0.52911,2,2,13.3,-8.03,0.98412,3,-4.54,-12.79,0.01588,1,2,2.03,-3.2,1,1,2,-5.95,-4.76,1,1,2,-7.34,1.8,1,1,2,-0.37,4.77,1,2,2,13.35,9.32,0.90804,3,-13.88,1.84,0.09196,1,3,1.28,9.33,1,1,3,11.31,8.51,1,1,3,20.88,7.73,1,1,3,28.33,4.64,1,1,3,36.15,1.4,1,1,3,35.77,-4.53,1],"hull":15,"edges":[0,2,2,4,4,6,6,8,8,10,10,12,12,14,14,16,16,18,26,28,0,28,18,20,20,22,22,24,24,26],"width":49,"height":50}},"Усик левый":{"Усик левый":{"type":"mesh","uvs":[1,1,0,1,0,0,1,0],"triangles":[1,2,3,1,3,0],"vertices":[1,14,34.04,-46.15,1,1,14,39.82,3.51,1,1,14,83.53,-1.58,1,1,14,77.75,-51.24,1],"hull":4,"edges":[0,2,2,4,4,6,0,6],"width":50,"height":44}},"Усик правый":{"Усик правый":{"type":"mesh","uvs":[1,1,0,1,0,0,1,0],"triangles":[1,2,3,1,3,0],"vertices":[1,14,24.12,-1.71,1,1,14,30.71,54.91,1,1,14,68.45,50.52,1,1,14,61.86,-6.1,1],"hull":4,"edges":[0,2,2,4,4,6,0,6],"width":57,"height":38}},"закрытые глаза":{"закрытые глаза":{"type":"mesh","uvs":[1,1,0,1,0,0,1,0],"triangles":[1,2,3,1,3,0],"vertices":[1,14,9.87,-27.39,1,1,14,15.65,22.28,1,1,14,56.37,17.54,1,1,14,50.59,-32.13,1],"hull":4,"edges":[0,2,2,4,4,6,0,6],"width":50,"height":41}}}}],"animations":{"angry":{"slots":{"Розовая подушка":{"attachment":[{"time":1.3,"name":"Розовая подушка"}]},"Тень розовой подушки_action":{"attachment":[{"time":0.9,"name":null},{"time":1.3,"name":"Тень розовой подушки"}]},"закрытые глаза":{"attachment":[{"name":null}]}},"bones":{"womb":{"rotate":[{"angle":2.89,"curve":0.067,"c2":0.29,"c3":0.75},{"time":0.5,"angle":-1.39,"curve":"stepped"},{"time":0.8333,"angle":-1.39},{"time":1,"angle":-0.8},{"time":1.3333,"angle":2.89}]},"body1":{"rotate":[{"angle":-23.4,"curve":0.067,"c2":0.29,"c3":0.75},{"time":0.5,"angle":-30.16,"curve":"stepped"},{"time":0.8333,"angle":-30.16},{"time":1,"angle":-43.44},{"time":1.3333,"angle":-23.4}]},"body2":{"rotate":[{"angle":14.32,"curve":0.067,"c2":0.29,"c3":0.75},{"time":0.5,"angle":10.32},{"time":0.8333,"angle":15.39,"curve":"stepped"},{"time":1,"angle":15.39},{"time":1.3333,"angle":14.32}]},"hand_r_IK":{"translate":[{"x":-25.32,"y":16.25}]},"hand_r1":{"rotate":[{"angle":-23.65},{"time":0.5,"angle":-18.1,"curve":"stepped"},{"time":0.8333,"angle":-18.1},{"time":1,"angle":-15.61},{"time":1.3333,"angle":-23.65}]},"hand_r2":{"rotate":[{"angle":33.05},{"time":0.5,"angle":28.86,"curve":"stepped"},{"time":0.8333,"angle":28.86},{"time":1,"angle":23.13},{"time":1.3333,"angle":33.05}]},"hand_l_IK":{"rotate":[{"time":0.8333},{"time":1,"angle":15.01},{"time":1.3333}],"translate":[{"x":-2.25,"y":-2.75,"curve":0.067,"c2":0.29,"c3":0.75},{"time":0.5,"x":-68.25,"y":5.39,"curve":"stepped"},{"time":0.8333,"x":-68.25,"y":5.39},{"time":1,"x":8.76,"y":15.05},{"time":1.3333,"x":-2.25,"y":-2.75}]},"hand_l1":{"rotate":[{"angle":-19.07},{"time":0.5,"angle":67.87,"curve":"stepped"},{"time":0.8333,"angle":67.87},{"time":1,"angle":31.86},{"time":1.3333,"angle":-19.07}]},"hand_l2":{"rotate":[{"angle":45.8},{"time":0.5,"angle":107.83,"curve":"stepped"},{"time":0.8333,"angle":107.83},{"time":1,"angle":10.57},{"time":1.3333,"angle":45.8}]},"arm_l":{"rotate":[{"angle":-26.18,"curve":"stepped"},{"time":0.8333,"angle":-26.18},{"time":1,"angle":94.98},{"time":1.3333,"angle":-26.18}],"translate":[{"x":4,"y":3.83,"curve":"stepped"},{"time":0.8333,"x":4,"y":3.83},{"time":1,"x":-0.27,"y":1.97},{"time":1.3333,"x":4,"y":3.83}],"scale":[{"x":0.684}]},"head":{"rotate":[{"angle":1.96},{"time":0.5,"angle":-4.24},{"time":0.8333,"angle":-9.97,"curve":"stepped"},{"time":1,"angle":-9.97},{"time":1.3333,"angle":1.96}]},"leg_IK":{"translate":[{"x":-7.7,"curve":0.067,"c2":0.29,"c3":0.75},{"time":0.5,"x":-13.57,"y":4.52,"curve":"stepped"},{"time":0.8333,"x":-13.57,"y":4.52},{"time":1,"x":-1.21,"y":4.52},{"time":1.3333,"x":-7.7}]},"leg1":{"rotate":[{"angle":-1.93},{"time":0.5,"angle":6.28,"curve":"stepped"},{"time":0.8333,"angle":6.28},{"time":1,"angle":-6.67},{"time":1.3333,"angle":-1.93}]},"leg2":{"rotate":[{"angle":5.12},{"time":0.5,"angle":-14.68,"curve":"stepped"},{"time":0.8333,"angle":-14.68},{"time":1,"angle":30.93},{"time":1.3333,"angle":5.12}]},"hip":{"translate":[{"x":-7.44}]},"pillow1_action":{"rotate":[{"time":0.8333},{"time":1,"angle":-69.1},{"time":1.2333,"angle":166.82}],"translate":[{"time":0.4667},{"time":0.6667,"x":-2.21},{"time":0.8333,"x":-0.55},{"time":1,"x":151.53,"y":43.93,"curve":0.25,"c3":0.75},{"time":1.2333,"x":63.64,"y":-23.9,"curve":"stepped"},{"time":1.4667,"x":63.64,"y":-23.9},{"time":1.6667,"x":63.64,"y":-326.83}],"scale":[{"time":0.8333},{"time":0.9333,"x":0.9,"y":0.834},{"time":1,"curve":0.25,"c3":0.75},{"time":1.2333,"x":3,"y":3},{"time":1.3667,"x":3.26,"y":3},{"time":1.4667,"x":3,"y":3},{"time":1.6667,"x":3,"y":3.481}]}},"deform":{"default":{"Зрачок левый":{"Зрачок левый":[{"time":0.5,"vertices":[0.18468,-0.5877,0.18468,-0.5877,0.18468,-0.5877,0.18468,-0.5877]},{"time":0.8333,"vertices":[-2.06042,4.81361,-2.06042,4.81361,-2.06042,4.81361,-2.06042,4.81361]}]},"Зрачок правый":{"Зрачок правый":[{"time":0.5,"vertices":[0.29382,0.09232]},{"time":0.8333,"vertices":[-1.76659,4.90594,-2.06042,4.81361,-2.06042,4.81361,-2.06042,4.81361]}]}}},"drawOrder":[{"time":0.8333,"offsets":[{"slot":"Розовая подушка_action","offset":2}]},{"time":1.0333,"offsets":[{"slot":"Розовая подушка_action","offset":21}]}]},"angry2":{"slots":{"закрытые глаза":{"attachment":[{"name":null}]}},"bones":{"womb":{"rotate":[{},{"time":0.3333,"angle":4.74},{"time":0.5333,"angle":2.82},{"time":0.7333,"angle":5.12},{"time":0.9333,"angle":5.76},{"time":1.1333,"angle":7.27},{"time":1.3333,"angle":6.22},{"time":1.5}]},"body1":{"rotate":[{},{"time":0.3333,"angle":-19.54},{"time":1.1667,"angle":-42.48},{"time":1.5}]},"body2":{"rotate":[{"time":0.3333},{"time":1.1667,"angle":18.83},{"time":1.5}]},"hand_r_IK":{"rotate":[{"angle":-6.34}],"translate":[{},{"time":0.3333,"x":23.42,"y":123.84,"curve":0.25,"c3":0.75},{"time":0.4333,"x":-7.26,"y":115.13,"curve":0.25,"c3":0.75},{"time":0.5333,"x":23.42,"y":123.84,"curve":0.25,"c3":0.75},{"time":0.6333,"x":-7.26,"y":115.13,"curve":0.25,"c3":0.75},{"time":0.7333,"x":23.42,"y":123.84,"curve":0.25,"c3":0.75},{"time":0.8333,"x":-7.26,"y":115.13,"curve":0.25,"c3":0.75},{"time":0.9333,"x":23.42,"y":123.84,"curve":0.25,"c3":0.75},{"time":1.0333,"x":-7.26,"y":115.13,"curve":0.25,"c3":0.75},{"time":1.1667,"x":23.42,"y":123.84},{"time":1.5}]},"hand_r1":{"rotate":[{"angle":2.05},{"time":0.3333,"angle":123.75},{"time":1.5,"angle":2.05}]},"hand_r2":{"rotate":[{"angle":-3.7},{"time":0.3333,"angle":-1.27},{"time":1.5,"angle":-3.7}]},"hand_l1":{"rotate":[{"angle":0.44},{"time":0.3333,"angle":-7.11},{"time":1.5,"angle":0.44}]},"hand_l2":{"rotate":[{"angle":-0.06},{"time":0.3333,"angle":60.54},{"time":1.5,"angle":-0.06}]},"head":{"rotate":[{},{"time":0.3333,"angle":21.76},{"time":1.1667,"angle":25.54},{"time":1.5}]},"leg_IK":{"translate":[{},{"time":0.3333,"x":-20.16,"curve":"stepped"},{"time":1.1667,"x":-20.16},{"time":1.5}]},"leg1":{"rotate":[{"angle":-2.17}]},"leg2":{"rotate":[{"angle":6}]},"leg3":{"rotate":[{"angle":-20.98},{"time":0.3333,"angle":25.13,"curve":"stepped"},{"time":1.1667,"angle":25.13},{"time":1.5,"angle":-20.98}]}},"deform":{"default":{"Зрачок левый":{"Зрачок левый":[{"vertices":[-0.08118,-0.69732]},{"time":0.3333,"vertices":[0.25143,6.00026,0.33262,6.69758,0.33262,6.69758,0.33262,6.69758],"curve":"stepped"},{"time":1.1667,"vertices":[0.25143,6.00026,0.33262,6.69758,0.33262,6.69758,0.33262,6.69758]},{"time":1.3333,"vertices":[-0.08118,-0.69732]}]},"Зрачок правый":{"Зрачок правый":[{},{"time":0.3333,"vertices":[0.3326,6.69756,0.33262,6.69758,0.33262,6.69758,0.33262,6.69758],"curve":"stepped"},{"time":1.1667,"vertices":[0.3326,6.69756,0.33262,6.69758,0.33262,6.69758,0.33262,6.69758]},{"time":1.3333}]}}}},"animation":{},"birth":{"slots":{"закрытые глаза":{"attachment":[{"name":null}]}},"bones":{"womb":{"rotate":[{"curve":0.132,"c2":0.27,"c3":0.75},{"time":0.5,"angle":7.6},{"time":0.6667,"angle":-1.15},{"time":0.8333}],"scale":[{"curve":0.132,"c2":0.27,"c3":0.75},{"time":0.5,"x":0.956,"y":1.058},{"time":0.6667,"x":1.005,"y":0.858},{"time":0.8333}]},"body2":{"rotate":[{},{"time":0.5,"angle":-7.07},{"time":0.6667,"angle":-1.78},{"time":0.8333,"angle":4.55},{"time":1,"angle":4.9},{"time":1.3333}]},"head":{"rotate":[{"time":0.5},{"time":0.6667,"angle":-10.55},{"time":0.8333,"angle":1.15},{"time":1,"angle":8.41},{"time":1.3333}]},"leg_IK":{"translate":[{},{"time":0.5,"x":-6.57},{"time":0.6667,"x":6.57,"y":24.48},{"time":0.8333,"x":-20.89,"y":1.79},{"time":1,"x":-7.16,"y":1.79},{"time":1.3333}]},"hand_r_IK":{"rotate":[{"time":1,"angle":-6.34}]},"hand_r1":{"rotate":[{"time":1,"angle":-20.03}]},"hand_r2":{"rotate":[{"time":1,"angle":7.18}]},"hand_l_IK":{"translate":[{},{"time":0.5,"x":-12.6,"y":6.85},{"time":1,"x":-13.27,"y":-5.85},{"time":1.3333}]},"hand_l1":{"rotate":[{"time":1,"angle":-25.75}]},"hand_l2":{"rotate":[{"time":1,"angle":-10.23}]},"leg1":{"rotate":[{"time":1,"angle":4.46}]},"leg2":{"rotate":[{"time":1,"angle":-15.77}]}}},"breath":{"slots":{"закрытые глаза":{"attachment":[{"name":null}]}},"bones":{"womb":{"rotate":[{},{"time":1.6667,"angle":2.8,"curve":0.25,"c3":0.75},{"time":3.3333}]},"body1":{"rotate":[{},{"time":1.6667,"angle":-1.23,"curve":0.25,"c3":0.75},{"time":3.3333}]},"body2":{"rotate":[{},{"time":1.6667,"angle":-1.71,"curve":0.25,"c3":0.75},{"time":3.3333}],"scale":[{},{"time":1.6667,"x":1.021,"y":1.15,"curve":0.25,"c3":0.75},{"time":3.3333}]},"hand_l1":{"rotate":[{"angle":0.44},{"time":1.6667,"angle":-1.45,"curve":0.25,"c3":0.75},{"time":3.3333}]},"hand_l2":{"rotate":[{"angle":-0.06},{"time":1.6667,"angle":14.27,"curve":0.25,"c3":0.75},{"time":3.3333}]},"arm_l":{"rotate":[{},{"time":1.6667,"angle":-0.28,"curve":0.25,"c3":0.75},{"time":3.3333}],"scale":[{},{"time":1.6667,"x":0.668,"curve":0.25,"c3":0.75},{"time":3.3333}]},"head":{"rotate":[{},{"time":1.6667,"angle":-0.79,"curve":0.25,"c3":0.75},{"time":3.3333}]},"leg1":{"rotate":[{"angle":-2.17},{"time":1.6667,"angle":1.53,"curve":0.25,"c3":0.75},{"time":3.3333}]},"leg2":{"rotate":[{"angle":6},{"time":1.6667,"angle":-3.9,"curve":0.25,"c3":0.75},{"time":3.3333}]},"leg3":{"rotate":[{"angle":-20.98},{"time":1.6667,"angle":-16.44},{"time":3.3333,"angle":-20.98}]},"leg_IK":{"translate":[{},{"time":1.6667,"x":-1.71},{"time":3.3333}]},"hand_r_IK":{"rotate":[{"angle":-6.34}]},"hand_r1":{"rotate":[{"angle":2.05}]},"hand_r2":{"rotate":[{"angle":-3.7}]}}},"eat":{"slots":{"закрытые глаза":{"attachment":[{"name":null}]}},"bones":{"womb":{"rotate":[{"angle":2.11,"curve":0.25,"c3":0.75},{"time":0.5,"angle":4.34,"curve":"stepped"},{"time":1.8333,"angle":4.34,"curve":0.25,"c3":0.75},{"time":2.3333,"angle":2.11}]},"body1":{"rotate":[{"angle":-23.4}]},"body2":{"rotate":[{"angle":1.6,"curve":0.25,"c3":0.75},{"time":0.5,"angle":-0.91,"curve":"stepped"},{"time":1.8333,"angle":-0.91,"curve":0.25,"c3":0.75},{"time":2.3333,"angle":1.6}]},"hand_r_IK":{"translate":[{"x":8.02,"y":77.84,"curve":0.25,"c3":0.75},{"time":0.5,"x":1.64,"y":83.26,"curve":"stepped"},{"time":1.8333,"x":1.64,"y":83.26,"curve":0.25,"c3":0.75},{"time":2.3333,"x":8.02,"y":77.84}]},"hand_r1":{"rotate":[{"angle":-15.47},{"time":1.8333,"angle":87.42,"curve":0.25,"c3":0.75},{"time":2.3333,"angle":-15.47}]},"hand_r2":{"rotate":[{"angle":31.35},{"time":1.8333,"angle":69.69,"curve":0.25,"c3":0.75},{"time":2.3333,"angle":31.35}]},"hand_l_IK":{"translate":[{"x":-3.05,"y":-2.62,"curve":0.25,"c3":0.75},{"time":0.5,"x":-3.05,"y":0.57,"curve":"stepped"},{"time":1.8333,"x":-3.05,"y":0.57,"curve":0.25,"c3":0.75},{"time":2.3333,"x":-3.05,"y":-2.62}]},"hand_l1":{"rotate":[{"angle":-8.02},{"time":1.8333,"angle":-0.1,"curve":0.25,"c3":0.75},{"time":2.3333,"angle":-8.02}]},"hand_l2":{"rotate":[{"angle":57.82},{"time":1.8333,"angle":54.57,"curve":0.25,"c3":0.75},{"time":2.3333,"angle":57.82}]},"arm_l":{"rotate":[{"angle":-34.34}],"translate":[{"x":2.41,"y":1.41}],"scale":[{"x":0.723}]},"head":{"rotate":[{"angle":18.41,"curve":0.25,"c3":0.75},{"time":0.5,"angle":9.28,"curve":0.25,"c3":0.75},{"time":0.8333,"angle":2.22,"curve":0.25,"c3":0.75},{"time":1.1667,"angle":12.5,"curve":0.25,"c3":0.75},{"time":1.5,"angle":8.37,"curve":0.25,"c3":0.75},{"time":1.8333,"angle":12.63,"curve":0.25,"c3":0.75},{"time":2.3333,"angle":18.41}]},"leg_IK":{"translate":[{"x":-7.7}]},"leg1":{"rotate":[{"angle":-1.93}]},"leg2":{"rotate":[{"angle":5.12}]},"hip":{"translate":[{"x":-7.44}]}},"path":{"happy_hand_left_path_constr":{"position":[{"position":0.5}]}},"deform":{"default":{"happy_hand_left_path":{"happy_hand_right_path":[{"vertices":[26.67481,-2.33656,26.67998,-2.155,34.97398,-2.155,26.67999,10.22697,26.67999,10.22697,26.67999,10.22697]}]},"happy_hand_right_path":{"happy_hand_right_path":[{"offset":1,"vertices":[21.966,0,21.966,0,21.966,0,34.34798,0,34.34798,0,34.34798]}]}}},"drawOrder":[{"offsets":[{"slot":"Кисть правая","offset":-9}]}]},"happy":{"slots":{"закрытые глаза":{"attachment":[{"name":null}]}},"bones":{"womb":{"rotate":[{"angle":2.11,"curve":0.381,"c2":0.59,"c3":0.729},{"time":0.2667,"angle":4.71},{"time":0.5333,"angle":2.11,"curve":0.381,"c2":0.59,"c3":0.729},{"time":0.8,"angle":4.71},{"time":1.0667,"angle":2.11}]},"body1":{"rotate":[{"angle":-23.4},{"time":0.2667,"angle":-45.16},{"time":0.5333,"angle":-23.4},{"time":0.8,"angle":-45.16},{"time":1.0667,"angle":-23.4}]},"body2":{"rotate":[{"angle":1.6},{"time":0.2667,"angle":26.57},{"time":0.5333,"angle":1.6},{"time":0.8,"angle":26.57},{"time":1.0667,"angle":1.6}]},"hand_r_IK":{"translate":[{"x":-4.8,"y":130.25},{"time":0.3333,"x":-4.42,"y":145.45}]},"hand_r1":{"rotate":[{"angle":-15.47}]},"hand_r2":{"rotate":[{"angle":31.35}]},"hand_l_IK":{"translate":[{"x":-3.05,"y":-2.62}]},"hand_l1":{"rotate":[{"angle":-8.02}]},"hand_l2":{"rotate":[{"angle":57.82}]},"arm_l":{"rotate":[{"angle":-34.34},{"time":0.5333,"angle":134.41},{"time":1.0667,"angle":-34.34}],"translate":[{"x":2.41,"y":1.41}],"scale":[{"x":0.723}]},"head":{"rotate":[{"angle":3.82}]},"leg_IK":{"translate":[{"x":-7.7},{"time":0.2667,"x":-13.46,"y":4.32},{"time":0.5333,"x":-7.7},{"time":0.8,"x":-13.46,"y":4.32},{"time":1.0667,"x":-7.7}]},"leg1":{"rotate":[{"angle":-1.93}]},"leg2":{"rotate":[{"angle":5.12}]},"hip":{"translate":[{"x":-7.44}]}},"path":{"happy_hand_left_path_constr":{"position":[{"position":0.5},{"time":0.5333,"position":1},{"time":1.0667,"position":1.5}],"mix":[{}]},"happy_hand_right_path_constr":{"position":[{},{"time":0.5333,"position":0.5},{"time":1.0667,"position":1}],"mix":[{}]}},"deform":{"default":{"happy_hand_left_path":{"happy_hand_right_path":[{"vertices":[26.67481,-2.33656,26.67998,-2.155,34.97398,-2.155,26.67999,10.22697,26.67999,10.22697,26.67999,10.22697]}]},"happy_hand_right_path":{"happy_hand_right_path":[{"offset":1,"vertices":[21.966,0,21.966,0,21.966,0,34.34798,0,34.34798,0,34.34798]}]}}},"drawOrder":[{"offsets":[{"slot":"Матка","offset":1}]}]},"hi":{"slots":{"Тень розовой подушки_action":{"attachment":[{"time":0.8667,"name":null},{"time":2.5667,"name":"Тень розовой подушки"}]},"закрытые глаза":{"attachment":[{"name":null}]}},"bones":{"womb":{"rotate":[{"angle":2.89,"curve":0.067,"c2":0.29,"c3":0.75},{"time":0.5,"angle":-1.39,"curve":"stepped"},{"time":0.8333,"angle":-1.39},{"time":1.1667,"angle":-0.04},{"time":1.5,"angle":-2.14},{"time":1.8333,"angle":0.29},{"time":2.1333,"angle":-0.8},{"time":2.5667,"angle":2.89}]},"body1":{"rotate":[{"angle":-23.4,"curve":0.067,"c2":0.29,"c3":0.75},{"time":0.5,"angle":-30.16,"curve":"stepped"},{"time":0.8333,"angle":-30.16},{"time":1.1667,"angle":-43.44},{"time":1.5,"angle":-35.24},{"time":1.8333,"angle":-44.9},{"time":2.1333,"angle":-43.44},{"time":2.5667,"angle":-23.4}]},"body2":{"rotate":[{"angle":14.32,"curve":0.067,"c2":0.29,"c3":0.75},{"time":0.5,"angle":10.32},{"time":0.8333,"angle":15.39,"curve":"stepped"},{"time":2.1333,"angle":15.39},{"time":2.5667,"angle":14.32}]},"hand_r_IK":{"rotate":[{"angle":-6.34}],"translate":[{"x":-25.32,"y":16.25},{"time":0.5,"x":-40.35,"y":16.25,"curve":"stepped"},{"time":2.1333,"x":-40.35,"y":16.25},{"time":2.5667,"x":-25.32,"y":16.25}]},"hand_r1":{"rotate":[{"angle":-23.65},{"time":0.5,"angle":-18.1,"curve":"stepped"},{"time":0.8333,"angle":-18.1},{"time":1.1667,"angle":-15.61,"curve":"stepped"},{"time":2.1333,"angle":-15.61},{"time":2.5667,"angle":-23.65}]},"hand_r2":{"rotate":[{"angle":33.05},{"time":0.5,"angle":28.86,"curve":"stepped"},{"time":0.8333,"angle":28.86},{"time":1.1667,"angle":23.13,"curve":"stepped"},{"time":2.1333,"angle":23.13},{"time":2.5667,"angle":33.05}]},"hand_l_IK":{"rotate":[{"time":0.8333},{"time":1.1667,"angle":15.01,"curve":"stepped"},{"time":2.3667,"angle":15.01},{"time":2.8}],"translate":[{"x":-2.25,"y":-2.75,"curve":0.067,"c2":0.29,"c3":0.75},{"time":0.5,"x":-68.25,"y":5.39,"curve":"stepped"},{"time":0.8333,"x":-68.25,"y":5.39},{"time":1.1667,"x":8.76,"y":15.05},{"time":1.4333,"x":-84.7,"y":40.59},{"time":1.7,"x":22.49,"y":28.23},{"time":1.9,"x":-66.09,"y":25.88},{"time":2.1667,"x":22.49,"y":28.23},{"time":2.3667,"x":-66.09,"y":25.88},{"time":2.8,"x":-2.25,"y":-2.75}]},"hand_l1":{"rotate":[{"angle":-19.07},{"time":0.5,"angle":67.87,"curve":"stepped"},{"time":0.8333,"angle":67.87},{"time":1.1667,"angle":31.86},{"time":2.1333,"angle":98.39},{"time":2.5667,"angle":-19.07}]},"hand_l2":{"rotate":[{"angle":45.8},{"time":0.5,"angle":107.83,"curve":"stepped"},{"time":0.8333,"angle":107.83},{"time":1.1667,"angle":10.57},{"time":2.1333,"angle":-10.23},{"time":2.5667,"angle":45.8}]},"arm_l":{"rotate":[{"angle":-26.18,"curve":"stepped"},{"time":0.8333,"angle":-26.18},{"time":1.1667,"angle":94.98},{"time":1.5,"angle":137.3},{"time":1.8333,"angle":94.98},{"time":2.1333,"angle":137.3},{"time":2.5667,"angle":-26.18}],"translate":[{"x":4,"y":3.83,"curve":"stepped"},{"time":0.8333,"x":4,"y":3.83},{"time":1.1667,"x":-0.27,"y":1.97,"curve":"stepped"},{"time":2.1333,"x":-0.27,"y":1.97},{"time":2.5667,"x":4,"y":3.83}],"scale":[{"x":0.684}]},"head":{"rotate":[{"angle":1.96},{"time":0.5,"angle":-4.24},{"time":0.8333,"angle":-9.97,"curve":"stepped"},{"time":2.1333,"angle":-9.97},{"time":2.5667,"angle":1.96}]},"leg_IK":{"translate":[{"x":-7.7,"curve":0.067,"c2":0.29,"c3":0.75},{"time":0.5,"x":-13.57,"y":4.52,"curve":"stepped"},{"time":2.1333,"x":-13.57,"y":4.52},{"time":2.5667,"x":-7.7}]},"leg1":{"rotate":[{"angle":-1.93},{"time":0.5,"angle":6.28,"curve":"stepped"},{"time":0.8333,"angle":6.28},{"time":1.1667,"angle":-6.67,"curve":"stepped"},{"time":2.1333,"angle":-6.67},{"time":2.5667,"angle":-1.93}]},"leg2":{"rotate":[{"angle":5.12},{"time":0.5,"angle":-14.68,"curve":"stepped"},{"time":0.8333,"angle":-14.68},{"time":1.1667,"angle":30.93,"curve":"stepped"},{"time":2.1333,"angle":30.93},{"time":2.5667,"angle":5.12}]},"hip":{"translate":[{"x":-7.44}]},"pillow1_action":{"rotate":[{"time":0.8333},{"time":1.1667,"angle":-69.1},{"time":1.4333,"angle":35.14},{"time":1.5333,"angle":5.06},{"time":1.7,"angle":-70.99},{"time":1.8,"angle":-21.76},{"time":1.9,"angle":32.45},{"time":2,"angle":5.06},{"time":2.1667,"angle":-70.99},{"time":2.2667,"angle":-21.76},{"time":2.3667,"angle":32.45},{"time":2.5667}],"translate":[{"time":0.4667},{"time":0.6667,"x":-2.21},{"time":0.8333,"x":-0.55},{"time":1.1667,"x":150.74,"y":41.95},{"time":1.3,"x":68.95,"y":78.5},{"time":1.4333,"x":-5.74,"y":82.66},{"time":1.5333,"x":48.41,"y":96.98},{"time":1.6,"x":113.28,"y":83.06},{"time":1.7,"x":152.87,"y":43.87},{"time":1.7333,"x":133,"y":70.03},{"time":1.8,"x":92.95,"y":97.42},{"time":1.9,"x":10.46,"y":70.91},{"time":2,"x":48.41,"y":96.98},{"time":2.0667,"x":113.28,"y":83.06},{"time":2.1667,"x":152.87,"y":43.87},{"time":2.2,"x":133,"y":70.03},{"time":2.2667,"x":92.95,"y":97.42},{"time":2.3667,"x":10.46,"y":70.91},{"time":2.5667}],"scale":[{"time":0.8333},{"time":1.1,"x":0.9,"y":0.834},{"time":1.1667,"curve":"stepped"},{"time":2.5667},{"time":2.6667,"x":1.07,"y":1.067},{"time":2.8}]}},"deform":{"default":{"Зрачок левый":{"Зрачок левый":[{"time":0.5,"vertices":[0.18468,-0.5877,0.18468,-0.5877,0.18468,-0.5877,0.18468,-0.5877]},{"time":0.8333,"vertices":[-2.06042,4.81361,-2.06042,4.81361,-2.06042,4.81361,-2.06042,4.81361],"curve":"stepped"},{"time":2.3333,"vertices":[-2.06042,4.81361,-2.06042,4.81361,-2.06042,4.81361,-2.06042,4.81361]},{"time":2.5667,"vertices":[0.18468,-0.5877,0.18468,-0.5877,0.18468,-0.5877,0.18468,-0.5877]}]},"Зрачок правый":{"Зрачок правый":[{"time":0.5,"vertices":[0.29382,0.09232]},{"time":0.8333,"vertices":[-1.76659,4.90594,-2.06042,4.81361,-2.06042,4.81361,-2.06042,4.81361],"curve":"stepped"},{"time":2.3333,"vertices":[-1.76659,4.90594,-2.06042,4.81361,-2.06042,4.81361,-2.06042,4.81361]},{"time":2.5667,"vertices":[0.29382,0.09232]}]}}}},"sleep":{"slots":{"Глаз левый":{"attachment":[{"name":null}]},"Глаз правый":{"attachment":[{"name":null}]}},"bones":{"womb":{"rotate":[{},{"time":1.6667,"angle":2.8,"curve":0.25,"c3":0.75},{"time":3.3333}]},"body1":{"rotate":[{},{"time":1.6667,"angle":-1.23,"curve":0.25,"c3":0.75},{"time":3.3333}]},"body2":{"rotate":[{},{"time":1.6667,"angle":-1.71,"curve":0.25,"c3":0.75},{"time":3.3333}],"scale":[{},{"time":1.6667,"x":1.021,"y":1.15,"curve":0.25,"c3":0.75},{"time":3.3333}]},"hand_l1":{"rotate":[{},{"time":1.6667,"angle":-1.45,"curve":0.25,"c3":0.75},{"time":3.3333}]},"hand_l2":{"rotate":[{},{"time":1.6667,"angle":14.27,"curve":0.25,"c3":0.75},{"time":3.3333}]},"arm_l":{"rotate":[{},{"time":1.6667,"angle":-0.28,"curve":0.25,"c3":0.75},{"time":3.3333}],"scale":[{},{"time":1.6667,"x":0.668,"curve":0.25,"c3":0.75},{"time":3.3333}]},"head":{"rotate":[{},{"time":1.6667,"angle":-0.79,"curve":0.25,"c3":0.75},{"time":3.3333}]},"leg1":{"rotate":[{},{"time":1.6667,"angle":1.53,"curve":0.25,"c3":0.75},{"time":3.3333}]},"leg2":{"rotate":[{},{"time":1.6667,"angle":-3.9,"curve":0.25,"c3":0.75},{"time":3.3333}]},"leg3":{"rotate":[{"angle":-20.98},{"time":1.6667,"angle":-16.44},{"time":3.3333,"angle":-20.98}]},"leg_IK":{"translate":[{},{"time":1.6667,"x":-1.71},{"time":3.3333}]}}},"tap":{"slots":{"Глаз левый":{"attachment":[{"time":0.5667,"name":null},{"time":0.6667,"name":"Глаз левый"},{"time":1,"name":null},{"time":1.1,"name":"Глаз левый"}]},"Глаз правый":{"attachment":[{"time":0.5667,"name":null},{"time":0.6667,"name":"Глаз правый"},{"time":1,"name":null},{"time":1.1,"name":"Глаз правый"}]},"закрытые глаза":{"attachment":[{"name":null},{"time":0.5667,"name":"закрытые глаза"},{"time":0.6667,"name":null},{"time":1,"name":"закрытые глаза"},{"time":1.1,"name":null}]}},"bones":{"womb":{"rotate":[{"curve":0.2,"c2":0.41,"c3":0.698,"c4":0.93},{"time":0.2333,"angle":3.75,"curve":0.25,"c3":0.75},{"time":0.4667,"angle":1.64},{"time":0.8333,"angle":2.89}]},"body1":{"rotate":[{"curve":0.2,"c2":0.41,"c3":0.698,"c4":0.93},{"time":0.2333,"angle":-26.88,"curve":0.25,"c3":0.75},{"time":0.4,"angle":-23.4}]},"body2":{"rotate":[{"curve":0.2,"c2":0.41,"c3":0.698,"c4":0.93},{"time":0.2333,"angle":24.55,"curve":0.25,"c3":0.75},{"time":0.4,"angle":1.6},{"time":0.5667,"angle":14.32}]},"hand_r_IK":{"translate":[{"curve":0.2,"c2":0.41,"c3":0.698,"c4":0.93},{"time":0.2333,"x":-25.32,"y":16.25}]},"hand_r1":{"rotate":[{"angle":2.05}]},"hand_r2":{"rotate":[{"angle":-3.7}]},"hand_l_IK":{"translate":[{"curve":0.2,"c2":0.41,"c3":0.698,"c4":0.93},{"time":0.2333,"x":-5.79,"y":-2.18,"curve":0.25,"c3":0.75},{"time":0.4667,"x":-2.25,"y":-2.75}]},"hand_l1":{"rotate":[{"angle":0.44}]},"hand_l2":{"rotate":[{"angle":-0.06}]},"arm_l":{"rotate":[{},{"time":0.4,"angle":-34.34},{"time":0.5667,"angle":-26.18}],"translate":[{"time":0.2333},{"time":0.4,"x":2.41,"y":1.41},{"time":0.5667,"x":3.25,"y":2.37},{"time":0.8,"x":4,"y":3.83}],"scale":[{},{"time":0.2333,"x":0.723,"curve":"stepped"},{"time":0.5667,"x":0.723},{"time":0.8,"x":0.684}]},"head":{"rotate":[{"curve":0.2,"c2":0.41,"c3":0.698,"c4":0.93},{"time":0.2333,"angle":33.34,"curve":0.25,"c3":0.75},{"time":0.5,"angle":-11.11,"curve":0.25,"c3":0.75},{"time":0.8333,"angle":1.96,"curve":"stepped"},{"time":1.3333,"angle":1.96}]},"leg_IK":{"translate":[{"curve":0.2,"c2":0.41,"c3":0.698,"c4":0.93},{"time":0.2333,"x":-7.7}]},"leg1":{"rotate":[{"angle":-2.17}]},"leg2":{"rotate":[{"angle":6}]},"hip":{"translate":[{},{"time":0.3333,"x":-7.44}]}}}}}